midi_const/__init__.py
midi_const/_utils.py
midi_const-0.1.2.dist-info/licenses/LICENSE
midi_const-0.1.2.dist-info/WHEEL
midi_const-0.1.2.dist-info/METADATA
midi_const-0.1.2.dist-info/RECORD
